{
  "timestamp": 1769414455,
  "data": {
    "AED": 3.6725,
    "AFN": 65.783924,
    "ALL": 81.476713,
    "AMD": 373.726749,
    "ANG": 1.79,
    "AOA": 912.215,
    "ARS": 1434.494,
    "AUD": 1.446375,
    "AWG": 1.8015,
    "AZN": 1.7,
    "BAM": 1.649601,
    "BBD": 2,
    "BDT": 121.101194,
    "BGN": 1.650795,
    "BHD": 0.377032,
    "BIF": 2931.968085,
    "BMD": 1,
    "BND": 1.266257,
    "BOB": 6.841175,
    "BRL": 5.323,
    "BSD": 1,
    "BTC": 0.000011392668,
    "BTN": 90.873591,
    "BWP": 13.732114,
    "BYN": 2.802608,
    "BZD": 1.991043,
    "CAD": 1.369079,
    "CDF": 2262.128148,
    "CHF": 0.778358,
    "CLP": 869.565217,
    "CNY": 6.9576,
    "CNH": 6.9559,
    "COP": 3570.779663,
    "CRC": 489.956422,
    "CUC": 1,
    "CUP": 25.75,
    "CVE": 93.002386,
    "CZK": 20.4831,
    "DJF": 176.296714,
    "DKK": 6.3041,
    "DOP": 62.37269,
    "DZD": 129.257764,
    "EGP": 47.0905,
    "ERN": 15,
    "ETB": 154.208383,
    "EUR": 0.844083,
    "FJD": 2.21345,
    "FKP": 0.732531,
    "GBP": 0.732531,
    "GEL": 2.691758,
    "GGP": 0.732531,
    "GHS": 10.791024,
    "GIP": 0.732531,
    "GMD": 72.9972,
    "GNF": 8671.460737,
    "GTQ": 7.598524,
    "GYD": 207.124607,
    "HKD": 7.795955,
    "HNL": 26.113874,
    "HRK": 6.359415,
    "HTG": 129.839257,
    "HUF": 322.51,
    "IDR": 16780.467078,
    "ILS": 3.138025,
    "IMP": 0.732531,
    "INR": 91.576283,
    "IQD": 1296.963914,
    "IRR": 42086,
    "ISK": 123.08,
    "JEP": 0.732531,
    "JMD": 155.83472,
    "JOD": 0.709,
    "JPY": 153.917733,
    "KES": 127.6,
    "KGS": 87.4496,
    "KHR": 3984.377427,
    "KMF": 415.239886,
    "KPW": 900,
    "KRW": 1441.124849,
    "KWD": 0.30689,
    "KYD": 0.825057,
    "KZT": 498.368105,
    "LAK": 21393.247744,
    "LBP": 88653.338635,
    "LKR": 306.702956,
    "LRD": 183.140823,
    "LSL": 15.978863,
    "LTL": -1,
    "LVL": -1,
    "LYD": 6.298841,
    "MAD": 9.068121,
    "MDL": 16.949248,
    "MGA": 4478.682373,
    "MKD": 51.974169,
    "MMK": 2099.9,
    "MNT": 3560,
    "MOP": 7.951485,
    "MRU": 39.580469,
    "MUR": 45.519999,
    "MVR": 15.45,
    "MWK": 1716.666477,
    "MXN": 17.383153,
    "MYR": 3.971,
    "MZN": 63.830001,
    "NAD": 15.978863,
    "NGN": 1408.06,
    "NIO": 36.428505,
    "NOK": 9.749944,
    "NPR": 145.398801,
    "NZD": 1.67865,
    "OMR": 0.3845,
    "PAB": 1,
    "PEN": 3.32123,
    "PGK": 4.234108,
    "PHP": 58.956499,
    "PKR": 276.999935,
    "PLN": 3.552971,
    "PYG": 6620.182614,
    "QAR": 3.60935,
    "RON": 4.3008,
    "RSD": 99.134183,
    "RUB": 75.749376,
    "RWF": 1443.892712,
    "SAR": 3.750077,
    "SBD": 8.12361,
    "SCR": 14.663796,
    "SDG": 601.5,
    "SEK": 8.918429,
    "SGD": 1.269798,
    "SHP": 0.732531,
    "SLL": 20969.5,
    "SOS": 564.770623,
    "SRD": 38.121,
    "STD": 22281.8,
    "SVC": 8.662171,
    "SYP": 13002,
    "SZL": 15.974832,
    "THB": 31.049357,
    "TJS": 9.256267,
    "TMT": 3.457306,
    "TND": 2.882024,
    "TOP": 2.40776,
    "TRY": 43.381316,
    "TTD": 6.724808,
    "TWD": 31.509999,
    "TZS": 2555,
    "UAH": 42.686961,
    "UGX": 3499.467073,
    "USD": 1,
    "UYU": 37.523069,
    "UZS": 12015.77508,
    "VES": 354.498866,
    "VND": 26188.294282,
    "VUV": 121.3,
    "WST": 2.7678,
    "XAF": 553.682442,
    "XAG": 0.009239,
    "XAU": 0.000196,
    "XCD": 2.70255,
    "XOF": 553.682442,
    "XPF": 100.725948,
    "YER": 238.268497,
    "ZAR": 16.045932,
    "ZMW": 19.42207,
    "ZWL": 322
  }
}