{
  "timestamp": 1773878686,
  "data": {
    "AED": 3.6725,
    "AFN": 63.999997,
    "ALL": 83.223522,
    "AMD": 377.472089,
    "ANG": 1.79,
    "AOA": 915.377,
    "ARS": 1394.494,
    "AUD": 1.422981,
    "AWG": 1.8,
    "AZN": 1.7,
    "BAM": 1.696351,
    "BBD": 2,
    "BDT": 122.885293,
    "BGN": 1.706312,
    "BHD": 0.377589,
    "BIF": 2969.539001,
    "BMD": 1,
    "BND": 1.278723,
    "BOB": 6.920298,
    "BRL": 5.2637,
    "BSD": 1,
    "BTC": 0.000014023466,
    "BTN": 92.084062,
    "BWP": 13.580799,
    "BYN": 2.990906,
    "BZD": 2.014154,
    "CAD": 1.373116,
    "CDF": 2292.441897,
    "CHF": 0.792611,
    "CLP": 917.431193,
    "CNY": 6.87305,
    "CNH": 6.898545,
    "COP": 3706.02,
    "CRC": 467.742498,
    "CUC": 1,
    "CUP": 25.75,
    "CVE": 96.202115,
    "CZK": 21.354449,
    "DJF": 177.862377,
    "DKK": 6.518425,
    "DOP": 60.545078,
    "DZD": 132.399569,
    "EGP": 52.3337,
    "ERN": 15,
    "ETB": 156.623266,
    "EUR": 0.872307,
    "FJD": 2.22225,
    "FKP": 0.753868,
    "GBP": 0.753868,
    "GEL": 2.715,
    "GGP": 0.753868,
    "GHS": 10.905,
    "GIP": 0.753868,
    "GMD": 74.000005,
    "GNF": 8778.556718,
    "GTQ": 7.671559,
    "GYD": 209.520271,
    "HKD": 7.83725,
    "HNL": 26.557012,
    "HRK": 6.573183,
    "HTG": 131.246057,
    "HUF": 343.149729,
    "IDR": 17045.97095,
    "ILS": 3.10035,
    "IMP": 0.753868,
    "INR": 93.176755,
    "IQD": 1311.112142,
    "IRR": 1315000,
    "ISK": 124.92,
    "JEP": 0.753868,
    "JMD": 157.24946,
    "JOD": 0.709,
    "JPY": 159.770667,
    "KES": 129.618582,
    "KGS": 87.45,
    "KHR": 4010.129564,
    "KMF": 428.000124,
    "KPW": 900,
    "KRW": 1506.750602,
    "KWD": 0.30666,
    "KYD": 0.834501,
    "KZT": 483.110851,
    "LAK": 21473.502937,
    "LBP": 89535.04501,
    "LKR": 311.84471,
    "LRD": 183.350071,
    "LSL": 16.758183,
    "LTL": -1,
    "LVL": -1,
    "LYD": 6.386305,
    "MAD": 9.372911,
    "MDL": 17.370247,
    "MGA": 4169.733693,
    "MKD": 53.789804,
    "MMK": 2099.81,
    "MNT": 3569.47,
    "MOP": 8.084959,
    "MRU": 40.070806,
    "MUR": 46.510004,
    "MVR": 15.46,
    "MWK": 1736.323254,
    "MXN": 17.854861,
    "MYR": 3.9155,
    "MZN": 63.899993,
    "NAD": 16.757618,
    "NGN": 1355.53,
    "NIO": 36.80007,
    "NOK": 9.605273,
    "NPR": 147.335539,
    "NZD": 1.726222,
    "OMR": 0.384499,
    "PAB": 1,
    "PEN": 3.423379,
    "PGK": 4.313743,
    "PHP": 59.769003,
    "PKR": 279.581608,
    "PLN": 3.730113,
    "PYG": 6472.557568,
    "QAR": 3.643578,
    "RON": 4.4423,
    "RSD": 102.473,
    "RUB": 83.875369,
    "RWF": 1460.683375,
    "SAR": 3.75419,
    "SBD": 8.04524,
    "SCR": 13.999572,
    "SDG": 601,
    "SEK": 9.403343,
    "SGD": 1.28347,
    "SHP": 0.753868,
    "SLL": 20969.5,
    "SOS": 572.320899,
    "SRD": 37.375,
    "STD": 22281.8,
    "SVC": 8.762663,
    "SYP": 13002,
    "SZL": 16.76022,
    "THB": 32.84,
    "TJS": 9.578717,
    "TMT": 3.5,
    "TND": 2.92343,
    "TOP": 2.40776,
    "TRY": 44.316702,
    "TTD": 6.788467,
    "TWD": 32.0462,
    "TZS": 2603.73,
    "UAH": 44.042966,
    "UGX": 3767.705684,
    "USD": 1,
    "UYU": 40.500205,
    "UZS": 12172.5,
    "VES": 450.942783,
    "VND": 26312.331424,
    "VUV": 119.389,
    "WST": 2.73372,
    "XAF": 572.196078,
    "XAG": 0.013138,
    "XAU": 0.000207,
    "XCD": 2.70255,
    "XOF": 572.196078,
    "XPF": 104.09395,
    "YER": 238.575051,
    "ZAR": 16.990199,
    "ZMW": 19.449511,
    "ZWL": 322
  }
}