{
  "timestamp": 1767801713,
  "data": {
    "AED": 3.6725,
    "AFN": 66.238019,
    "ALL": 82.599348,
    "AMD": 381.650955,
    "ANG": 1.79,
    "AOA": 912.286,
    "ARS": 1472.168451,
    "AUD": 1.486466,
    "AWG": 1.8025,
    "AZN": 1.7,
    "BAM": 1.674071,
    "BBD": 2,
    "BDT": 122.264167,
    "BGN": 1.673328,
    "BHD": 0.376997,
    "BIF": 2960.741114,
    "BMD": 1,
    "BND": 1.282216,
    "BOB": 6.928752,
    "BRL": 5.3994,
    "BSD": 1,
    "BTC": 0.000010991833,
    "BTN": 89.986587,
    "BWP": 13.362265,
    "BYN": 2.941735,
    "BZD": 2.012206,
    "CAD": 1.381742,
    "CDF": 2300.027712,
    "CHF": 0.796982,
    "CLP": 895.51,
    "CNY": 7.004,
    "CNH": 6.989449,
    "COP": 3726.689763,
    "CRC": 497.393966,
    "CUC": 1,
    "CUP": 25.75,
    "CVE": 94.381546,
    "CZK": 20.7703,
    "DJF": 178.175647,
    "DKK": 6.395137,
    "DOP": 63.511626,
    "DZD": 129.901139,
    "EGP": 47.303399,
    "ERN": 15,
    "ETB": 155.84071,
    "EUR": 0.855837,
    "FJD": 2.27344,
    "FKP": 0.741965,
    "GBP": 0.741965,
    "GEL": 2.69,
    "GGP": 0.741965,
    "GHS": 10.782149,
    "GIP": 0.741965,
    "GMD": 73.500003,
    "GNF": 8759.059421,
    "GTQ": 7.669329,
    "GYD": 209.332482,
    "HKD": 7.786278,
    "HNL": 26.37359,
    "HRK": 6.44619,
    "HTG": 131.020562,
    "HUF": 329.497178,
    "IDR": 16762.927644,
    "ILS": 3.172705,
    "IMP": 0.741965,
    "INR": 89.86842,
    "IQD": 1310.717382,
    "IRR": 42086,
    "ISK": 125.99,
    "JEP": 0.741965,
    "JMD": 158.393858,
    "JOD": 0.709,
    "JPY": 156.652286,
    "KES": 129,
    "KGS": 87.4435,
    "KHR": 4017.822662,
    "KMF": 421.999693,
    "KPW": 900,
    "KRW": 1448.320498,
    "KWD": 0.307193,
    "KYD": 0.833783,
    "KZT": 510.59226,
    "LAK": 21621.082516,
    "LBP": 89580.984135,
    "LKR": 310.27391,
    "LRD": 178.16178,
    "LSL": 16.436758,
    "LTL": -1,
    "LVL": -1,
    "LYD": 5.422455,
    "MAD": 9.223224,
    "MDL": 16.700158,
    "MGA": 4622.012137,
    "MKD": 52.683161,
    "MMK": 2099.9,
    "MNT": 3560,
    "MOP": 8.0234,
    "MRU": 39.851406,
    "MUR": 46.449998,
    "MVR": 15.46,
    "MWK": 1734.939726,
    "MXN": 17.973098,
    "MYR": 4.058,
    "MZN": 63.909994,
    "NAD": 16.436758,
    "NGN": 1425.28,
    "NIO": 36.823047,
    "NOK": 10.084357,
    "NPR": 143.977923,
    "NZD": 1.731478,
    "OMR": 0.384507,
    "PAB": 1,
    "PEN": 3.363805,
    "PGK": 4.26692,
    "PHP": 59.252999,
    "PKR": 280.22748,
    "PLN": 3.60423,
    "PYG": 6756.051118,
    "QAR": 3.647895,
    "RON": 4.355,
    "RSD": 100.394214,
    "RUB": 80.593451,
    "RWF": 1458.285323,
    "SAR": 3.749883,
    "SBD": 8.130216,
    "SCR": 13.894063,
    "SDG": 601,
    "SEK": 9.19587,
    "SGD": 1.282373,
    "SHP": 0.741965,
    "SLL": 20969.5,
    "SOS": 570.834644,
    "SRD": 38.3,
    "STD": 22281.8,
    "SVC": 8.754676,
    "SYP": 13002,
    "SZL": 16.432564,
    "THB": 31.3875,
    "TJS": 9.248475,
    "TMT": 3.5,
    "TND": 2.923076,
    "TOP": 2.40776,
    "TRY": 43.040597,
    "TTD": 6.783418,
    "TWD": 31.473001,
    "TZS": 2475,
    "UAH": 42.624884,
    "UGX": 3625.292092,
    "USD": 1,
    "UYU": 38.962926,
    "UZS": 11974.728046,
    "VES": 307.769451,
    "VND": 26274.303731,
    "VUV": 121.3,
    "WST": 2.7678,
    "XAF": 561.392524,
    "XAG": 0.013055,
    "XAU": 0.000226,
    "XCD": 2.70255,
    "XOF": 561.392524,
    "XPF": 102.128566,
    "YER": 238.400076,
    "ZAR": 16.479508,
    "ZMW": 20.943594,
    "ZWL": 322
  }
}