{
  "timestamp": 1752019315,
  "data": {
    "AED": 3.673596,
    "AFN": 68.68,
    "ALL": 83.88,
    "AMD": 386,
    "ANG": -1,
    "AOA": 911.955,
    "ARS": 1,
    "AUD": 1.541305,
    "AWG": 1.79,
    "AZN": 1.705,
    "BAM": 1.674224,
    "BBD": 1.989998,
    "BDT": 122.5,
    "BGN": 1.674224,
    "BHD": 0.376081,
    "BIF": 2,
    "BMD": 1,
    "BND": 1.282299,
    "BOB": 6.96,
    "BRL": 5.479295,
    "BSD": 1,
    "BTC": -1,
    "BTN": 85.863914,
    "BWP": 13.404826,
    "BYN": 2.9569,
    "BZD": 2,
    "CAD": 1.369699,
    "CDF": 2,
    "CHF": 0.799799,
    "CLP": 948.32,
    "CNY": 7.178343,
    "CNH": -1,
    "COP": 4,
    "CRC": 506.68,
    "CUC": -1,
    "CUP": 24,
    "CVE": 94.388709,
    "CZK": 21.134979,
    "DJF": 177.6,
    "DKK": 6.387394,
    "DOP": 60.3824,
    "DZD": 129.6714,
    "EGP": 49.7566,
    "ERN": 15,
    "ETB": 136.5798,
    "EUR": 0.856017,
    "FJD": 2.306273,
    "FKP": 0.73948,
    "GBP": 0.73948,
    "GEL": 2.745,
    "GGP": -1,
    "GHS": 10.45,
    "GIP": 0.73948,
    "GMD": 71.59,
    "GNF": 8,
    "GTQ": 7.699,
    "GYD": 209.83,
    "HKD": 7.850392,
    "HNL": 26.0983,
    "HRK": 6.44966,
    "HTG": 131.6229,
    "HUF": 342.629657,
    "IDR": 16,
    "ILS": 3.370697,
    "IMP": -1,
    "INR": 85.863914,
    "IQD": 1,
    "IRR": 42,
    "ISK": 122.28,
    "JEP": -1,
    "JMD": 159.01,
    "JOD": 0.71,
    "JPY": 146.999853,
    "KES": 129.4,
    "KGS": 87.45,
    "KHR": 4,
    "KMF": 421.132733,
    "KPW": 2.2,
    "KRW": 1,
    "KWD": 0.3056,
    "KYD": 0.833333,
    "KZT": 520.05,
    "LAK": 21,
    "LBP": 89,
    "LKR": 300.65,
    "LRD": 199,
    "LSL": 17.882082,
    "LTL": 2.955655,
    "LVL": 0.601612,
    "LYD": 5.3883,
    "MAD": 8.9822,
    "MDL": 16.8,
    "MGA": 4,
    "MKD": 52.6384,
    "MMK": 3,
    "MNT": 3,
    "MOP": 8.093453,
    "MRU": 39.65,
    "MUR": 45.5491,
    "MVR": -1,
    "MWK": 1,
    "MXN": 18.714,
    "MYR": 4.249996,
    "MZN": 63.27,
    "NAD": 17.882082,
    "NGN": 1,
    "NIO": 36.6243,
    "NOK": 10.17909,
    "NPR": 137.382263,
    "NZD": 1.672799,
    "OMR": 0.38501,
    "PAB": 1,
    "PEN": 3.566,
    "PGK": 4.258944,
    "PHP": 56.615,
    "PKR": 284.529,
    "PLN": 3.637296,
    "PYG": 7,
    "QAR": 3.64,
    "RON": 4.348996,
    "RSD": 100.2,
    "RUB": 78.719921,
    "RWF": 1,
    "SAR": 3.751396,
    "SBD": 8.56531,
    "SCR": 14.3947,
    "SDG": 603.6508,
    "SEK": 9.58509,
    "SGD": 1.282299,
    "SHP": 0.73948,
    "SLL": 22,
    "SOS": 568,
    "SRD": 37.763,
    "STD": 20,
    "SVC": 8.75,
    "SYP": 6,
    "SZL": 17.882082,
    "THB": 32.683967,
    "TJS": 9.6531,
    "TMT": 3.491,
    "TND": 2.916,
    "TOP": 2.436944,
    "TRY": 40.16776,
    "TTD": 6.6989,
    "TWD": 29.146,
    "TZS": 2,
    "UAH": 41.7975,
    "UGX": 3,
    "USD": 1,
    "UYU": 40.613,
    "UZS": 12,
    "VES": 112.8285,
    "VND": 26,
    "VUV": 123.69,
    "WST": 2.829655,
    "XAF": 561.51031,
    "XAG": -1,
    "XAU": -1,
    "XCD": 2.68817,
    "XOF": 561.51031,
    "XPF": 102.149994,
    "YER": 250.5,
    "ZAR": 17.882082,
    "ZMW": 24.25,
    "ZWL": 68
  }
}