{
  "timestamp": 1763078518,
  "data": {
    "AED": 3.673,
    "AFN": 66.2624,
    "ALL": 83.2007,
    "AMD": 382.165,
    "ANG": 1.79,
    "AOA": 925.149,
    "ARS": 1408,
    "AUD": 1.5321,
    "AWG": 1.79,
    "AZN": 1.70025,
    "BAM": 1.68195,
    "BBD": 2,
    "BDT": 122.2,
    "BGN": 1.68195,
    "BHD": 0.377025,
    "BIF": 2952.14,
    "BMD": 1,
    "BND": 1.30135,
    "BOB": 6.8902,
    "BRL": 5.2982,
    "BSD": 1,
    "BTC": -1,
    "BTN": 88.7025,
    "BWP": 14.1343,
    "BYN": 3.41061,
    "BZD": 2,
    "CAD": 1.40395,
    "CDF": 2194.22,
    "CHF": 0.7934,
    "CLP": 929.75,
    "CNY": 7.09585,
    "CNH": -1,
    "COP": 3748.57,
    "CRC": 501.535,
    "CUC": 1,
    "CUP": 24,
    "CVE": 95.255,
    "CZK": 20.7955,
    "DJF": 178.036,
    "DKK": 6.42211,
    "DOP": 64.2905,
    "DZD": 130.143,
    "EGP": 47.19,
    "ERN": 15,
    "ETB": 153.821,
    "EUR": 0.859956,
    "FJD": 2.28754,
    "FKP": 0.760052,
    "GBP": 0.760052,
    "GEL": 2.70535,
    "GGP": 0.760052,
    "GHS": 10.9775,
    "GIP": 0.760052,
    "GMD": 72.8806,
    "GNF": 8679.6,
    "GTQ": 7.66136,
    "GYD": 209.18,
    "HKD": 7.77075,
    "HNL": 26.2774,
    "HRK": 6.4793,
    "HTG": 130.988,
    "HUF": 330.52,
    "IDR": 16723,
    "ILS": 3.22595,
    "IMP": 0.760052,
    "INR": 88.7765,
    "IQD": 1310,
    "IRR": 42000,
    "ISK": 126.415,
    "JEP": 0.760052,
    "JMD": 160.176,
    "JOD": 0.709,
    "JPY": 154.68,
    "KES": 129.2,
    "KGS": 87.459,
    "KHR": 4011,
    "KMF": 423.069,
    "KPW": 899.982,
    "KRW": 1471.35,
    "KWD": 0.306695,
    "KYD": 0.82,
    "KZT": 524.345,
    "LAK": 21693.1,
    "LBP": 89550,
    "LKR": 305.7,
    "LRD": 183.296,
    "LSL": 17.0474,
    "LTL": -1,
    "LVL": -1,
    "LYD": 5.456,
    "MAD": 9.2564,
    "MDL": 16.8346,
    "MGA": 4467.73,
    "MKD": 52.965,
    "MMK": 2100,
    "MNT": 3575.22,
    "MOP": 8.00385,
    "MRU": 39.7649,
    "MUR": 45.8536,
    "MVR": 15.4208,
    "MWK": 1733.67,
    "MXN": 18.3189,
    "MYR": 4.1275,
    "MZN": 63.8844,
    "NAD": 17.0509,
    "NGN": 1455.43,
    "NIO": 36.8136,
    "NOK": 10.027,
    "NPR": 141.87,
    "NZD": 1.77038,
    "OMR": 0.38499,
    "PAB": 1,
    "PEN": 3.37145,
    "PGK": 4.24538,
    "PHP": 58.926,
    "PKR": 280.7,
    "PLN": 3.638,
    "PYG": 7049.1,
    "QAR": 3.64105,
    "RON": 4.37253,
    "RSD": 100.77,
    "RUB": 80.7,
    "RWF": 1451.45,
    "SAR": 3.75,
    "SBD": 8.1103,
    "SCR": 14.8684,
    "SDG": 599.971,
    "SEK": 9.40818,
    "SGD": 1.30135,
    "SHP": 0.761296,
    "SLL": 23270.4,
    "SOS": 570.5,
    "SRD": 38.6246,
    "STD": -1,
    "SVC": 8.75,
    "SYP": 11062,
    "SZL": 17.0446,
    "THB": 32.345,
    "TJS": 9.26885,
    "TMT": 3.5,
    "TND": 2.93505,
    "TOP": 2.40183,
    "TRY": 42.2903,
    "TTD": 6.75145,
    "TWD": 31.14,
    "TZS": 2429.54,
    "UAH": 41.75,
    "UGX": 3614.29,
    "USD": 1,
    "UYU": 39.745,
    "UZS": 11985,
    "VES": 234.578,
    "VND": 26349.5,
    "VUV": 121.825,
    "WST": 2.79057,
    "XAF": 564.092,
    "XAG": -1,
    "XAU": -1,
    "XCD": 2.7,
    "XOF": 564.092,
    "XPF": 102.76,
    "YER": 238.477,
    "ZAR": 17.0535,
    "ZMW": 22.525,
    "ZWL": 13.7313
  }
}