{
  "timestamp": 1770019638,
  "data": {
    "AED": 3.67295,
    "AFN": 65.6069,
    "ALL": 81.5087,
    "AMD": 378.436,
    "ANG": 1.79,
    "AOA": 918.213,
    "ARS": 1447,
    "AUD": 1.4403,
    "AWG": 1.79,
    "AZN": 1.70015,
    "BAM": 1.65045,
    "BBD": 2,
    "BDT": 122.3,
    "BGN": 1.665,
    "BHD": 0.377005,
    "BIF": 2978.12,
    "BMD": 1,
    "BND": 1.27195,
    "BOB": 6.87425,
    "BRL": 5.2618,
    "BSD": 1,
    "BTC": -1,
    "BTN": 91.694,
    "BWP": 13.6986,
    "BYN": 2.87656,
    "BZD": 2,
    "CAD": 1.36525,
    "CDF": 2233.28,
    "CHF": 0.77335,
    "CLP": 873.55,
    "CNY": 6.95175,
    "CNH": 6.9524,
    "COP": 3680.41,
    "CRC": 495.255,
    "CUC": 1,
    "CUP": 24,
    "CVE": 93.47,
    "CZK": 20.5223,
    "DJF": 178.37,
    "DKK": 6.30169,
    "DOP": 63.0045,
    "DZD": 129.444,
    "EGP": 47.18,
    "ERN": 15,
    "ETB": 152.908,
    "EUR": 0.843775,
    "FJD": 2.22866,
    "FKP": 0.730941,
    "GBP": 0.730914,
    "GEL": 2.6929,
    "GGP": 0.730941,
    "GHS": 10.9493,
    "GIP": 0.730941,
    "GMD": 72.2838,
    "GNF": 8754.07,
    "GTQ": 7.66661,
    "GYD": 209.215,
    "HKD": 7.8099,
    "HNL": 26.3566,
    "HRK": 6.35795,
    "HTG": 131.002,
    "HUF": 321.461,
    "IDR": 16795,
    "ILS": 3.10775,
    "IMP": 0.730941,
    "INR": 91.5487,
    "IQD": 1310,
    "IRR": 42000,
    "ISK": 122.355,
    "JEP": 0.730914,
    "JMD": 156.038,
    "JOD": 0.709,
    "JPY": 154.915,
    "KES": 129,
    "KGS": 87.4253,
    "KHR": 4021.5,
    "KMF": 415.142,
    "KPW": 900.027,
    "KRW": 1458.49,
    "KWD": 0.3053,
    "KYD": 0.82,
    "KZT": 504.8,
    "LAK": 21501.7,
    "LBP": 89550,
    "LKR": 309.35,
    "LRD": 183.169,
    "LSL": 16.202,
    "LTL": -1,
    "LVL": -1,
    "LYD": 6.2717,
    "MAD": 9.1277,
    "MDL": 16.9037,
    "MGA": 4457.91,
    "MKD": 51.735,
    "MMK": 2100,
    "MNT": 3561.5,
    "MOP": 8.04425,
    "MRU": 39.7015,
    "MUR": 45.6625,
    "MVR": 15.23,
    "MWK": 1733.67,
    "MXN": 17.4839,
    "MYR": 3.942,
    "MZN": 63.5608,
    "NAD": 16.2025,
    "NGN": 1445.71,
    "NIO": 36.787,
    "NOK": 9.68156,
    "NPR": 146.475,
    "NZD": 1.66431,
    "OMR": 0.384995,
    "PAB": 1,
    "PEN": 3.3695,
    "PGK": 4.27899,
    "PHP": 58.9015,
    "PKR": 279.85,
    "PLN": 3.55545,
    "PYG": 6647.35,
    "QAR": 3.64115,
    "RON": 4.29967,
    "RSD": 99.095,
    "RUB": 77.21,
    "RWF": 1455.85,
    "SAR": 3.7507,
    "SBD": 8.1103,
    "SCR": 14.4551,
    "SDG": 600.171,
    "SEK": 8.91372,
    "SGD": 1.27195,
    "SHP": 0.731984,
    "SLL": 24011.7,
    "SOS": 571.5,
    "SRD": 38.113,
    "STD": -1,
    "SVC": 8.75,
    "SYP": 11059.6,
    "SZL": 16.2,
    "THB": 31.63,
    "TJS": 9.318,
    "TMT": 3.5,
    "TND": 2.84535,
    "TOP": 2.33318,
    "TRY": 43.4975,
    "TTD": 6.74445,
    "TWD": 31.609,
    "TZS": 2547.89,
    "UAH": 42.65,
    "UGX": 3572.38,
    "USD": 1,
    "UYU": 38.8,
    "UZS": 12230,
    "VES": 369.792,
    "VND": 26017.5,
    "VUV": 119.725,
    "WST": 2.71518,
    "XAF": 553.522,
    "XAG": -1,
    "XAU": -1,
    "XCD": 2.7,
    "XOF": 553.522,
    "XPF": 100.845,
    "YER": 238.33,
    "ZAR": 16.2032,
    "ZMW": 19.6325,
    "ZWL": 13.7313
  }
}