{
  "timestamp": 1761091318,
  "data": {
    "AED": 3.673,
    "AFN": 66.4667,
    "ALL": 83.2256,
    "AMD": 382.342,
    "ANG": 1.79,
    "AOA": 925.696,
    "ARS": 1490.25,
    "AUD": 1.54012,
    "AWG": 1.79,
    "AZN": 1.6992,
    "BAM": 1.686,
    "BBD": 2,
    "BDT": 122.025,
    "BGN": 1.6859,
    "BHD": 0.376975,
    "BIF": 2950.12,
    "BMD": 1,
    "BND": 1.29845,
    "BOB": 6.907,
    "BRL": 5.38835,
    "BSD": 1,
    "BTC": -1,
    "BTN": 87.9575,
    "BWP": 14.2248,
    "BYN": 3.40478,
    "BZD": 2,
    "CAD": 1.4017,
    "CDF": 2252.48,
    "CHF": 0.79675,
    "CLP": 953.39,
    "CNY": 7.1224,
    "CNH": -1,
    "COP": 3892,
    "CRC": 503.665,
    "CUC": 1,
    "CUP": 24,
    "CVE": 95.485,
    "CZK": 20.9512,
    "DJF": 177.695,
    "DKK": 6.43768,
    "DOP": 63.7855,
    "DZD": 130.479,
    "EGP": 47.53,
    "ERN": 15,
    "ETB": 149.68,
    "EUR": 0.861995,
    "FJD": 2.30044,
    "FKP": 0.748083,
    "GBP": 0.748083,
    "GEL": 2.709,
    "GGP": 0.748083,
    "GHS": 10.7007,
    "GIP": 0.748083,
    "GMD": 72.5825,
    "GNF": 8661.74,
    "GTQ": 7.655,
    "GYD": 209.215,
    "HKD": 7.77135,
    "HNL": 26.2247,
    "HRK": 6.49505,
    "HTG": 130.945,
    "HUF": 335.588,
    "IDR": 16595,
    "ILS": 3.29355,
    "IMP": 0.748083,
    "INR": 87.997,
    "IQD": 1310,
    "IRR": 42000,
    "ISK": 122.06,
    "JEP": 0.748083,
    "JMD": 159.774,
    "JOD": 0.709,
    "JPY": 151.865,
    "KES": 129.2,
    "KGS": 87.25,
    "KHR": 4030.5,
    "KMF": 424.095,
    "KPW": 900.009,
    "KRW": 1431,
    "KWD": 0.30632,
    "KYD": 0.82,
    "KZT": 538.665,
    "LAK": 21692.5,
    "LBP": 89550,
    "LKR": 303.15,
    "LRD": 183.06,
    "LSL": 17.3863,
    "LTL": -1,
    "LVL": -1,
    "LYD": 5.4294,
    "MAD": 9.2402,
    "MDL": 16.8434,
    "MGA": 4486.66,
    "MKD": 53.09,
    "MMK": 2100,
    "MNT": 3590,
    "MOP": 8.0045,
    "MRU": 39.9963,
    "MUR": 45.231,
    "MVR": 15.1925,
    "MWK": 1733.67,
    "MXN": 18.4354,
    "MYR": 4.2295,
    "MZN": 63.895,
    "NAD": 17.3952,
    "NGN": 1486.57,
    "NIO": 36.8361,
    "NOK": 10.0616,
    "NPR": 140.77,
    "NZD": 1.7411,
    "OMR": 0.384995,
    "PAB": 1,
    "PEN": 3.3909,
    "PGK": 4.12797,
    "PHP": 58.254,
    "PKR": 281.075,
    "PLN": 3.655,
    "PYG": 7085.65,
    "QAR": 3.6453,
    "RON": 4.38109,
    "RSD": 101.03,
    "RUB": 81.375,
    "RWF": 1448.52,
    "SAR": 3.7504,
    "SBD": 8.19001,
    "SCR": 14.713,
    "SDG": 600.171,
    "SEK": 9.42962,
    "SGD": 1.29845,
    "SHP": 0.749709,
    "SLL": 23141.4,
    "SOS": 571.5,
    "SRD": 38.9443,
    "STD": -1,
    "SVC": 8.75,
    "SYP": 11060,
    "SZL": 17.3863,
    "THB": 32.885,
    "TJS": 9.2625,
    "TMT": 3.5,
    "TND": 2.9352,
    "TOP": 2.36016,
    "TRY": 41.9707,
    "TTD": 6.7628,
    "TWD": 30.691,
    "TZS": 2452.6,
    "UAH": 41.45,
    "UGX": 3481,
    "USD": 1,
    "UYU": 39.815,
    "UZS": 12011,
    "VES": 210.02,
    "VND": 26343,
    "VUV": 121.935,
    "WST": 2.76817,
    "XAF": 565.461,
    "XAG": -1,
    "XAU": -1,
    "XCD": 2.7,
    "XOF": 565.461,
    "XPF": 103.02,
    "YER": 238.83,
    "ZAR": 17.4003,
    "ZMW": 22.6831,
    "ZWL": 13.7313
  }
}