{
  "timestamp": 1748995351,
  "data": {
    "AED": 3.6729,
    "AFN": 68.8702,
    "ALL": 86.3409,
    "AMD": 384.354,
    "ANG": 1.79,
    "AOA": 923.928,
    "ARS": 1184.25,
    "AUD": 1.54643,
    "AWG": 1.79,
    "AZN": 1.69965,
    "BAM": 1.7175,
    "BBD": 2,
    "BDT": 122.2,
    "BGN": 1.7177,
    "BHD": 0.37698,
    "BIF": 2943.63,
    "BMD": 1,
    "BND": 1.2889,
    "BOB": 6.91,
    "BRL": 5.63885,
    "BSD": 1,
    "BTC": -1,
    "BTN": 85.6245,
    "BWP": 13.459,
    "BYN": 3.27467,
    "BZD": 2,
    "CAD": 1.37125,
    "CDF": 2862.96,
    "CHF": 0.8227,
    "CLP": 940.905,
    "CNY": 7.18805,
    "CNH": -1,
    "COP": 4108.3,
    "CRC": 509.06,
    "CUC": 1,
    "CUP": 24,
    "CVE": 97.265,
    "CZK": 21.8519,
    "DJF": 177.884,
    "DKK": 6.55141,
    "DOP": 59.035,
    "DZD": 131.502,
    "EGP": 49.67,
    "ERN": 15,
    "ETB": 134.088,
    "EUR": 0.878117,
    "FJD": 2.26783,
    "FKP": 0.738962,
    "GBP": 0.738962,
    "GEL": 2.731,
    "GGP": 0.738962,
    "GHS": 10.1092,
    "GIP": 0.738962,
    "GMD": 71.6349,
    "GNF": 8637.45,
    "GTQ": 7.68333,
    "GYD": 209.215,
    "HKD": 7.8454,
    "HNL": 25.9939,
    "HRK": 6.6164,
    "HTG": 131.009,
    "HUF": 354.496,
    "IDR": 16285,
    "ILS": 3.518,
    "IMP": 0.738962,
    "INR": 85.7085,
    "IQD": 1310,
    "IRR": 42000,
    "ISK": 126.975,
    "JEP": 0.738962,
    "JMD": 158.645,
    "JOD": 0.709,
    "JPY": 143.825,
    "KES": 129.25,
    "KGS": 87.325,
    "KHR": 4010.5,
    "KMF": 432.021,
    "KPW": 900.047,
    "KRW": 1378.72,
    "KWD": 0.30675,
    "KYD": 0.82,
    "KZT": 512.65,
    "LAK": 21591.7,
    "LBP": 89600,
    "LKR": 299.35,
    "LRD": 199.293,
    "LSL": 17.8452,
    "LTL": -1,
    "LVL": -1,
    "LYD": 5.4527,
    "MAD": 9.197,
    "MDL": 17.2122,
    "MGA": 4519.88,
    "MKD": 53.765,
    "MMK": 2100,
    "MNT": 3573,
    "MOP": 8.08075,
    "MRU": 39.6487,
    "MUR": 45.5053,
    "MVR": 15.335,
    "MWK": 1733.67,
    "MXN": 19.2356,
    "MYR": 4.245,
    "MZN": 63.6998,
    "NAD": 17.8553,
    "NGN": 1582.53,
    "NIO": 36.8061,
    "NOK": 10.1309,
    "NPR": 136.95,
    "NZD": 1.66472,
    "OMR": 0.385025,
    "PAB": 1,
    "PEN": 3.62345,
    "PGK": 4.07747,
    "PHP": 55.7,
    "PKR": 283.05,
    "PLN": 3.75225,
    "PYG": 7990.15,
    "QAR": 3.6453,
    "RON": 4.44191,
    "RSD": 102.925,
    "RUB": 78.975,
    "RWF": 1417.76,
    "SAR": 3.7507,
    "SBD": 8.25764,
    "SCR": 14.5501,
    "SDG": 600.451,
    "SEK": 9.61521,
    "SGD": 1.2889,
    "SHP": 0.739235,
    "SLL": 22621.5,
    "SOS": 571.5,
    "SRD": 36.71,
    "STD": -1,
    "SVC": 8.75,
    "SYP": 13005,
    "SZL": 17.8479,
    "THB": 32.62,
    "TJS": 10.0925,
    "TMT": 3.5,
    "TND": 2.952,
    "TOP": 2.35793,
    "TRY": 39.1494,
    "TTD": 6.7564,
    "TWD": 29.983,
    "TZS": 2690,
    "UAH": 41.25,
    "UGX": 3643,
    "USD": 1,
    "UYU": 41.695,
    "UZS": 12857.5,
    "VES": 97.2976,
    "VND": 26055,
    "VUV": 120.82,
    "WST": 2.74876,
    "XAF": 576.027,
    "XAG": -1,
    "XAU": -1,
    "XCD": 2.7,
    "XOF": 576.027,
    "XPF": 104.96,
    "YER": 243.556,
    "ZAR": 17.8541,
    "ZMW": 26.9253,
    "ZWL": 13.7313
  }
}