{
  "timestamp": 1783414847,
  "data": {
    "AED": 3.6729,
    "AFN": 65.2119,
    "ALL": 82.1666,
    "AMD": 367.376,
    "ANG": 1.79,
    "AOA": 936.315,
    "ARS": 1485.75,
    "AUD": 1.4404,
    "AWG": 1.79,
    "AZN": 1.69975,
    "BAM": 1.7115,
    "BBD": 2,
    "BDT": 123.25,
    "BGN": 1.7115,
    "BHD": 0.376995,
    "BIF": 2985.23,
    "BMD": 1,
    "BND": 1.29195,
    "BOB": 6.85795,
    "BRL": 5.1264,
    "BSD": 1,
    "BTC": -1,
    "BTN": 95.4,
    "BWP": 14.0944,
    "BYN": 2.86642,
    "BZD": 2,
    "CAD": 1.42135,
    "CDF": 2277.79,
    "CHF": 0.80635,
    "CLP": 928.5,
    "CNY": 6.79475,
    "CNH": 6.79475,
    "COP": 3352.16,
    "CRC": 452.7,
    "CUC": 1,
    "CUP": 24,
    "CVE": 96.925,
    "CZK": 21.1914,
    "DJF": 177.952,
    "DKK": 6.54078,
    "DOP": 58.921,
    "DZD": 133.173,
    "EGP": 48.845,
    "ERN": 15,
    "ETB": 158.991,
    "EUR": 0.875044,
    "FJD": 2.24921,
    "FKP": 0.746798,
    "GBP": 0.746742,
    "GEL": 2.6375,
    "GGP": 0.74677,
    "GHS": 11.3983,
    "GIP": 0.74677,
    "GMD": 73.2647,
    "GNF": 8762.61,
    "GTQ": 7.62543,
    "GYD": 209,
    "HKD": 7.84285,
    "HNL": 26.7686,
    "HRK": 6.5933,
    "HTG": 130.787,
    "HUF": 310.225,
    "IDR": 17967.8,
    "ILS": 3.01115,
    "IMP": 0.74677,
    "INR": 95.0675,
    "IQD": 1310,
    "IRR": 42000,
    "ISK": 126.005,
    "JEP": 0.746798,
    "JMD": 157.365,
    "JOD": 0.709,
    "JPY": 161.9,
    "KES": 129.25,
    "KGS": 87.4231,
    "KHR": 4034.75,
    "KMF": 430.512,
    "KPW": 899.982,
    "KRW": 1521.75,
    "KWD": 0.3076,
    "KYD": 0.82,
    "KZT": 470.895,
    "LAK": 22531.1,
    "LBP": 89550,
    "LKR": 334.75,
    "LRD": 181.624,
    "LSL": 16.248,
    "LTL": -1,
    "LVL": -1,
    "LYD": 6.3981,
    "MAD": 9.3644,
    "MDL": 17.59,
    "MGA": 4266.02,
    "MKD": 53.88,
    "MMK": 2100,
    "MNT": 3579,
    "MOP": 8.07815,
    "MRU": 39.9429,
    "MUR": 47.075,
    "MVR": 15.332,
    "MWK": 1733.67,
    "MXN": 17.4236,
    "MYR": 4.0725,
    "MZN": 63.4395,
    "NAD": 16.248,
    "NGN": 1367.13,
    "NIO": 36.7882,
    "NOK": 9.79848,
    "NPR": 152.13,
    "NZD": 1.75716,
    "OMR": 0.385005,
    "PAB": 1,
    "PEN": 3.3996,
    "PGK": 4.39754,
    "PHP": 61.4269,
    "PKR": 278.163,
    "PLN": 3.75725,
    "PYG": 6088,
    "QAR": 3.64115,
    "RON": 4.57959,
    "RSD": 102.7,
    "RUB": 76.61,
    "RWF": 1466.81,
    "SAR": 3.7553,
    "SBD": 8.09061,
    "SCR": 14.6397,
    "SDG": 600.171,
    "SEK": 9.64754,
    "SGD": 1.29195,
    "SHP": 0.747859,
    "SLL": 24096.7,
    "SOS": 571.5,
    "SRD": 37.5624,
    "STD": -1,
    "SVC": 8.75,
    "SYP": 11059.6,
    "SZL": 16.248,
    "THB": 33.2975,
    "TJS": 9.2415,
    "TMT": 3.5,
    "TND": 2.9519,
    "TOP": 2.37643,
    "TRY": 46.8402,
    "TTD": 6.7324,
    "TWD": 32.108,
    "TZS": 2629.58,
    "UAH": 44.35,
    "UGX": 3654.45,
    "USD": 1,
    "UYU": 40.245,
    "UZS": 12023.6,
    "VES": 674.087,
    "VND": 26295,
    "VUV": 119.775,
    "WST": 2.75862,
    "XAF": 574.016,
    "XAG": -1,
    "XAU": -1,
    "XCD": 2.7,
    "XOF": 574.014,
    "XPF": 104.565,
    "YER": 238.012,
    "ZAR": 16.2487,
    "ZMW": 18.3011,
    "ZWL": 66821.3
  }
}