{
  "timestamp": 1753286463,
  "data": {
    "AED": 3.6732,
    "AFN": 69.0091,
    "ALL": 83.0425,
    "AMD": 383.817,
    "ANG": 1.79,
    "AOA": 923.921,
    "ARS": 1259.5,
    "AUD": 1.51745,
    "AWG": 1.79,
    "AZN": 1.69965,
    "BAM": 1.66495,
    "BBD": 2,
    "BDT": 121.9,
    "BGN": 1.66795,
    "BHD": 0.376955,
    "BIF": 2939.28,
    "BMD": 1,
    "BND": 1.27735,
    "BOB": 6.8975,
    "BRL": 5.54055,
    "BSD": 1,
    "BTC": -1,
    "BTN": 86.4185,
    "BWP": 14.2349,
    "BYN": 3.27526,
    "BZD": 2,
    "CAD": 1.36125,
    "CDF": 2871.71,
    "CHF": 0.79375,
    "CLP": 947.47,
    "CNY": 7.1602,
    "CNH": -1,
    "COP": 4037.52,
    "CRC": 505.18,
    "CUC": 1,
    "CUP": 24,
    "CVE": 94.29,
    "CZK": 20.9407,
    "DJF": 177.598,
    "DKK": 6.35366,
    "DOP": 60.68,
    "DZD": 129.23,
    "EGP": 49.09,
    "ERN": 15,
    "ETB": 137.251,
    "EUR": 0.851281,
    "FJD": 2.24115,
    "FKP": 0.737273,
    "GBP": 0.737246,
    "GEL": 2.7085,
    "GGP": 0.737273,
    "GHS": 10.45,
    "GIP": 0.737273,
    "GMD": 72.194,
    "GNF": 8647.75,
    "GTQ": 7.6747,
    "GYD": 209.215,
    "HKD": 7.84995,
    "HNL": 26.1809,
    "HRK": 6.4141,
    "HTG": 131.145,
    "HUF": 339.406,
    "IDR": 16290,
    "ILS": 3.3288,
    "IMP": 0.737273,
    "INR": 86.3465,
    "IQD": 1310,
    "IRR": 42000,
    "ISK": 121.055,
    "JEP": 0.737273,
    "JMD": 159.691,
    "JOD": 0.709,
    "JPY": 146.57,
    "KES": 129.2,
    "KGS": 87.225,
    "KHR": 4009,
    "KMF": 418.808,
    "KPW": 900.01,
    "KRW": 1375.5,
    "KWD": 0.305175,
    "KYD": 0.82,
    "KZT": 538.79,
    "LAK": 21563.2,
    "LBP": 89600,
    "LKR": 301.7,
    "LRD": 200.008,
    "LSL": 17.544,
    "LTL": -1,
    "LVL": -1,
    "LYD": 5.4151,
    "MAD": 8.9885,
    "MDL": 16.8456,
    "MGA": 4407.69,
    "MKD": 52.885,
    "MMK": 2100,
    "MNT": 3578.75,
    "MOP": 8.0855,
    "MRU": 39.7727,
    "MUR": 45.4328,
    "MVR": 15.215,
    "MWK": 1733.67,
    "MXN": 18.5771,
    "MYR": 4.2275,
    "MZN": 63.9157,
    "NAD": 17.544,
    "NGN": 1527.67,
    "NIO": 36.7965,
    "NOK": 10.1092,
    "NPR": 138.26,
    "NZD": 1.65631,
    "OMR": 0.38502,
    "PAB": 1,
    "PEN": 3.5543,
    "PGK": 4.06421,
    "PHP": 56.791,
    "PKR": 284.7,
    "PLN": 3.6212,
    "PYG": 7482.5,
    "QAR": 3.6451,
    "RON": 4.3154,
    "RSD": 99.71,
    "RUB": 78.4,
    "RWF": 1440.03,
    "SAR": 3.7517,
    "SBD": 8.19001,
    "SCR": 14.5185,
    "SDG": 600.371,
    "SEK": 9.51519,
    "SGD": 1.27735,
    "SHP": 0.737382,
    "SLL": 22793.8,
    "SOS": 571.5,
    "SRD": 36.9778,
    "STD": -1,
    "SVC": 8.75,
    "SYP": 13005,
    "SZL": 17.545,
    "THB": 32.21,
    "TJS": 9.659,
    "TMT": 3.5,
    "TND": 2.8652,
    "TOP": 2.331,
    "TRY": 40.4525,
    "TTD": 6.77635,
    "TWD": 29.296,
    "TZS": 2605,
    "UAH": 41.4,
    "UGX": 3589.07,
    "USD": 1,
    "UYU": 39.995,
    "UZS": 12752.5,
    "VES": 120.273,
    "VND": 26150,
    "VUV": 119.735,
    "WST": 2.73261,
    "XAF": 558.411,
    "XAG": -1,
    "XAU": -1,
    "XCD": 2.7,
    "XOF": 558.411,
    "XPF": 101.74,
    "YER": 240.877,
    "ZAR": 17.5457,
    "ZMW": 23.3745,
    "ZWL": 13.7313
  }
}