{
  "timestamp": 1780273205,
  "data": {
    "AED": 3.67295,
    "AFN": 63.8318,
    "ALL": 81.9313,
    "AMD": 368.66,
    "ANG": 1.79,
    "AOA": 931.356,
    "ARS": 1409,
    "AUD": 1.39247,
    "AWG": 1.79,
    "AZN": 1.69975,
    "BAM": 1.67895,
    "BBD": 2,
    "BDT": 122.529,
    "BGN": 1.67895,
    "BHD": 0.377025,
    "BIF": 2981.88,
    "BMD": 1,
    "BND": 1.2769,
    "BOB": 6.88035,
    "BRL": 5.0347,
    "BSD": 1,
    "BTC": -1,
    "BTN": 95.005,
    "BWP": 13.947,
    "BYN": 2.74015,
    "BZD": 2,
    "CAD": 1.38005,
    "CDF": 2257.64,
    "CHF": 0.78255,
    "CLP": 889.589,
    "CNY": 6.7668,
    "CNH": 6.76375,
    "COP": 3681.04,
    "CRC": 452.94,
    "CUC": 1,
    "CUP": 24,
    "CVE": 95.075,
    "CZK": 20.8433,
    "DJF": 178.072,
    "DKK": 6.41536,
    "DOP": 58.2545,
    "DZD": 132.628,
    "EGP": 52.3832,
    "ERN": 15,
    "ETB": 157.43,
    "EUR": 0.858369,
    "FJD": 2.20604,
    "FKP": 0.743439,
    "GBP": 0.743467,
    "GEL": 2.65065,
    "GGP": 0.743439,
    "GHS": 11.7198,
    "GIP": 0.743439,
    "GMD": 72.5592,
    "GNF": 8770.01,
    "GTQ": 7.6203,
    "GYD": 209.215,
    "HKD": 7.83605,
    "HNL": 26.6407,
    "HRK": 6.4677,
    "HTG": 130.804,
    "HUF": 303.906,
    "IDR": 17851.5,
    "ILS": 2.81095,
    "IMP": 0.743439,
    "INR": 95.1332,
    "IQD": 1310,
    "IRR": 42000,
    "ISK": 123.09,
    "JEP": 0.743439,
    "JMD": 157.165,
    "JOD": 0.709,
    "JPY": 159.415,
    "KES": 129.45,
    "KGS": 87.4704,
    "KHR": 4022.5,
    "KMF": 422.314,
    "KPW": 899.972,
    "KRW": 1509.4,
    "KWD": 0.3095,
    "KYD": 0.82,
    "KZT": 485.705,
    "LAK": 21918.2,
    "LBP": 89550,
    "LKR": 330.27,
    "LRD": 182.555,
    "LSL": 16.2338,
    "LTL": -1,
    "LVL": -1,
    "LYD": 6.3459,
    "MAD": 9.1828,
    "MDL": 17.305,
    "MGA": 4183.3,
    "MKD": 53.01,
    "MMK": 2100,
    "MNT": 3573,
    "MOP": 8.0711,
    "MRU": 39.9655,
    "MUR": 47.3653,
    "MVR": 15.2101,
    "MWK": 1733.67,
    "MXN": 17.353,
    "MYR": 3.96757,
    "MZN": 63.5644,
    "NAD": 16.2435,
    "NGN": 1372.11,
    "NIO": 36.7496,
    "NOK": 9.24489,
    "NPR": 152.01,
    "NZD": 1.67266,
    "OMR": 0.385015,
    "PAB": 1,
    "PEN": 3.3996,
    "PGK": 4.3573,
    "PHP": 61.5248,
    "PKR": 278.463,
    "PLN": 3.6321,
    "PYG": 6012.5,
    "QAR": 3.64525,
    "RON": 4.5024,
    "RSD": 100.705,
    "RUB": 71,
    "RWF": 1463.54,
    "SAR": 3.75275,
    "SBD": 8.0289,
    "SCR": 14.3592,
    "SDG": 600.221,
    "SEK": 9.24712,
    "SGD": 1.2769,
    "SHP": 0.74474,
    "SLL": 24133.4,
    "SOS": 571.5,
    "SRD": 37.0646,
    "STD": -1,
    "SVC": 8.75,
    "SYP": 11059.6,
    "SZL": 16.2337,
    "THB": 32.57,
    "TJS": 9.194,
    "TMT": 3.5,
    "TND": 2.8941,
    "TOP": 2.34687,
    "TRY": 45.8971,
    "TTD": 6.726,
    "TWD": 31.448,
    "TZS": 2601.24,
    "UAH": 43.97,
    "UGX": 3772.4,
    "USD": 1,
    "UYU": 40.15,
    "UZS": 12001.4,
    "VES": 553.733,
    "VND": 26312.5,
    "VUV": 118.25,
    "WST": 2.7115,
    "XAF": 563.085,
    "XAG": -1,
    "XAU": -1,
    "XCD": 2.7,
    "XOF": 563.085,
    "XPF": 102.575,
    "YER": 238.583,
    "ZAR": 16.2421,
    "ZMW": 18.4119,
    "ZWL": 67236.2
  }
}