{
  "timestamp": 1769990606,
  "data": {
    "AED": 3.67295,
    "AFN": 65.5626,
    "ALL": 81.538,
    "AMD": 377.997,
    "ANG": 1.79,
    "AOA": 911.379,
    "ARS": 1447,
    "AUD": 1.4373,
    "AWG": 1.79,
    "AZN": 1.70025,
    "BAM": 1.64915,
    "BBD": 2,
    "BDT": 122.3,
    "BGN": 1.665,
    "BHD": 0.37701,
    "BIF": 2976.12,
    "BMD": 1,
    "BND": 1.27145,
    "BOB": 6.87425,
    "BRL": 5.2576,
    "BSD": 1,
    "BTC": -1,
    "BTN": 91.694,
    "BWP": 13.6147,
    "BYN": 2.84434,
    "BZD": 2,
    "CAD": 1.3627,
    "CDF": 2233.28,
    "CHF": 0.77285,
    "CLP": 873.55,
    "CNY": 6.95175,
    "CNH": 6.9568,
    "COP": 3679.7,
    "CRC": 495.255,
    "CUC": 1,
    "CUP": 24,
    "CVE": 93.4,
    "CZK": 20.5177,
    "DJF": 178.433,
    "DKK": 6.29698,
    "DOP": 63.0085,
    "DZD": 129.354,
    "EGP": 47.13,
    "ERN": 15,
    "ETB": 155.383,
    "EUR": 0.843206,
    "FJD": 2.22866,
    "FKP": 0.730327,
    "GBP": 0.73038,
    "GEL": 2.6914,
    "GGP": 0.730327,
    "GHS": 10.9075,
    "GIP": 0.730327,
    "GMD": 72.375,
    "GNF": 8754.07,
    "GTQ": 7.66661,
    "GYD": 209.215,
    "HKD": 7.80955,
    "HNL": 26.3566,
    "HRK": 6.353,
    "HTG": 131.002,
    "HUF": 321.367,
    "IDR": 16772.5,
    "ILS": 3.1018,
    "IMP": 0.730327,
    "INR": 91.694,
    "IQD": 1310,
    "IRR": 42000,
    "ISK": 122.265,
    "JEP": 0.730327,
    "JMD": 156.038,
    "JOD": 0.709,
    "JPY": 154.91,
    "KES": 129,
    "KGS": 87.4253,
    "KHR": 4021.5,
    "KMF": 414.821,
    "KPW": 900,
    "KRW": 1450.85,
    "KWD": 0.3053,
    "KYD": 0.82,
    "KZT": 504.17,
    "LAK": 21503,
    "LBP": 89550,
    "LKR": 309.25,
    "LRD": 183.169,
    "LSL": 16.07,
    "LTL": -1,
    "LVL": -1,
    "LYD": 6.2717,
    "MAD": 9.1161,
    "MDL": 16.8416,
    "MGA": 4457.91,
    "MKD": 51.735,
    "MMK": 2100,
    "MNT": 3561.92,
    "MOP": 8.04395,
    "MRU": 39.7015,
    "MUR": 45.4049,
    "MVR": 15.23,
    "MWK": 1733.67,
    "MXN": 17.4599,
    "MYR": 3.942,
    "MZN": 63.5608,
    "NAD": 16.1427,
    "NGN": 1445.71,
    "NIO": 36.787,
    "NOK": 9.64181,
    "NPR": 147.18,
    "NZD": 1.66044,
    "OMR": 0.384975,
    "PAB": 1,
    "PEN": 3.3695,
    "PGK": 4.27625,
    "PHP": 58.92,
    "PKR": 279.85,
    "PLN": 3.5529,
    "PYG": 6647.35,
    "QAR": 3.6445,
    "RON": 4.29512,
    "RSD": 99.075,
    "RUB": 76,
    "RWF": 1455.85,
    "SAR": 3.7507,
    "SBD": 8.1103,
    "SCR": 14.9461,
    "SDG": 600.171,
    "SEK": 8.91454,
    "SGD": 1.27145,
    "SHP": 0.731449,
    "SLL": 24011.7,
    "SOS": 571.5,
    "SRD": 38.113,
    "STD": -1,
    "SVC": 8.75,
    "SYP": 11059.6,
    "SZL": 16.1557,
    "THB": 31.55,
    "TJS": 9.318,
    "TMT": 3.5,
    "TND": 2.844,
    "TOP": 2.3546,
    "TRY": 43.4976,
    "TTD": 6.74445,
    "TWD": 31.6225,
    "TZS": 2569.83,
    "UAH": 42.65,
    "UGX": 3561.86,
    "USD": 1,
    "UYU": 38.8,
    "UZS": 12207.5,
    "VES": 369.792,
    "VND": 25930.1,
    "VUV": 119.76,
    "WST": 2.68061,
    "XAF": 553.095,
    "XAG": -1,
    "XAU": -1,
    "XCD": 2.7,
    "XOF": 553.095,
    "XPF": 100.76,
    "YER": 238.33,
    "ZAR": 16.177,
    "ZMW": 19.7502,
    "ZWL": 13.7313
  }
}