{
  "timestamp": 1758729688,
  "data": {
    "AED": 3.67295,
    "AFN": 67.5407,
    "ALL": 82.5739,
    "AMD": 382.815,
    "ANG": 1.79,
    "AOA": 923.388,
    "ARS": 1353,
    "AUD": 1.51872,
    "AWG": 1.79,
    "AZN": 1.69965,
    "BAM": 1.66585,
    "BBD": 2,
    "BDT": 121.7,
    "BGN": 1.66565,
    "BHD": 0.377045,
    "BIF": 2956.07,
    "BMD": 1,
    "BND": 1.28885,
    "BOB": 6.91,
    "BRL": 5.31905,
    "BSD": 1,
    "BTC": -1,
    "BTN": 88.7235,
    "BWP": 14.2248,
    "BYN": 3.38519,
    "BZD": 2,
    "CAD": 1.38965,
    "CDF": 2782.73,
    "CHF": 0.7952,
    "CLP": 954.025,
    "CNY": 7.13215,
    "CNH": -1,
    "COP": 3889.24,
    "CRC": 504.25,
    "CUC": 1,
    "CUP": 24,
    "CVE": 94.34,
    "CZK": 20.7061,
    "DJF": 177.824,
    "DKK": 6.35708,
    "DOP": 62.2195,
    "DZD": 129.205,
    "EGP": 48.16,
    "ERN": 15,
    "ETB": 143.606,
    "EUR": 0.851716,
    "FJD": 2.25581,
    "FKP": 0.743743,
    "GBP": 0.743743,
    "GEL": 2.7095,
    "GGP": 0.743716,
    "GHS": 12.3011,
    "GIP": 0.743743,
    "GMD": 72.6,
    "GNF": 8650.39,
    "GTQ": 7.6592,
    "GYD": 209.215,
    "HKD": 7.77865,
    "HNL": 26.1662,
    "HRK": 6.41735,
    "HTG": 131.002,
    "HUF": 333.081,
    "IDR": 16713,
    "ILS": 3.3604,
    "IMP": 0.743716,
    "INR": 88.7474,
    "IQD": 1310,
    "IRR": 42000,
    "ISK": 121.11,
    "JEP": 0.743716,
    "JMD": 159.349,
    "JOD": 0.709,
    "JPY": 148.735,
    "KES": 129.15,
    "KGS": 87.25,
    "KHR": 4011.75,
    "KMF": 419.024,
    "KPW": 900.031,
    "KRW": 1404.95,
    "KWD": 0.3047,
    "KYD": 0.82,
    "KZT": 542.535,
    "LAK": 21650.5,
    "LBP": 89550,
    "LKR": 302.45,
    "LRD": 180.014,
    "LSL": 17.3431,
    "LTL": -1,
    "LVL": -1,
    "LYD": 5.3967,
    "MAD": 9.0592,
    "MDL": 16.578,
    "MGA": 4427.94,
    "MKD": 52.48,
    "MMK": 2100,
    "MNT": 3592,
    "MOP": 8.01205,
    "MRU": 39.861,
    "MUR": 45.2895,
    "MVR": 15.19,
    "MWK": 1733.67,
    "MXN": 18.4456,
    "MYR": 4.21,
    "MZN": 63.9002,
    "NAD": 17.3238,
    "NGN": 1497.93,
    "NIO": 36.8204,
    "NOK": 9.94753,
    "NPR": 141.91,
    "NZD": 1.72043,
    "OMR": 0.38506,
    "PAB": 1,
    "PEN": 3.5067,
    "PGK": 4.17711,
    "PHP": 57.66,
    "PKR": 281.4,
    "PLN": 3.63415,
    "PYG": 7078.15,
    "QAR": 3.645,
    "RON": 4.32327,
    "RSD": 99.805,
    "RUB": 83.75,
    "RWF": 1447.05,
    "SAR": 3.7508,
    "SBD": 8.12678,
    "SCR": 15.1326,
    "SDG": 600.221,
    "SEK": 9.40644,
    "SGD": 1.28885,
    "SHP": 0.74402,
    "SLL": 23126.4,
    "SOS": 571.5,
    "SRD": 39.0411,
    "STD": -1,
    "SVC": 8.75,
    "SYP": 13005,
    "SZL": 17.3431,
    "THB": 32.095,
    "TJS": 9.4375,
    "TMT": 3.5,
    "TND": 2.90205,
    "TOP": 2.33918,
    "TRY": 41.4586,
    "TTD": 6.7637,
    "TWD": 30.35,
    "TZS": 2465,
    "UAH": 41.1,
    "UGX": 3495,
    "USD": 1,
    "UYU": 39.905,
    "UZS": 12213,
    "VES": 169.764,
    "VND": 26416.8,
    "VUV": 119.365,
    "WST": 2.73075,
    "XAF": 558.699,
    "XAG": -1,
    "XAU": -1,
    "XCD": 2.7,
    "XOF": 558.698,
    "XPF": 101.78,
    "YER": 239.377,
    "ZAR": 17.3526,
    "ZMW": 23.7575,
    "ZWL": 13.7313
  }
}