{
  "timestamp": 1778143723,
  "data": {
    "AED": 3.67305,
    "AFN": 64.2137,
    "ALL": 81.1351,
    "AMD": 370.05,
    "ANG": 1.79,
    "AOA": 927.123,
    "ARS": 1387.75,
    "AUD": 1.3776,
    "AWG": 1.79,
    "AZN": 1.70005,
    "BAM": 1.66165,
    "BBD": 2,
    "BDT": 122.7,
    "BGN": 1.66165,
    "BHD": 0.3773,
    "BIF": 2982.8,
    "BMD": 1,
    "BND": 1.2656,
    "BOB": 6.87925,
    "BRL": 4.92295,
    "BSD": 1,
    "BTC": -1,
    "BTN": 94.615,
    "BWP": 14.0449,
    "BYN": 2.81992,
    "BZD": 2,
    "CAD": 1.36265,
    "CDF": 2310.51,
    "CHF": 0.7777,
    "CLP": 892.5,
    "CNY": 6.8019,
    "CNH": 6.8016,
    "COP": 3709.77,
    "CRC": 457.825,
    "CUC": 1,
    "CUP": 24,
    "CVE": 94.1,
    "CZK": 20.655,
    "DJF": 178.216,
    "DKK": 6.34871,
    "DOP": 59.3935,
    "DZD": 132.122,
    "EGP": 52.72,
    "ERN": 15,
    "ETB": 156.961,
    "EUR": 0.849582,
    "FJD": 2.20459,
    "FKP": 0.734187,
    "GBP": 0.734187,
    "GEL": 2.685,
    "GGP": 0.734187,
    "GHS": 11.235,
    "GIP": 0.734187,
    "GMD": 72.9125,
    "GNF": 8749.74,
    "GTQ": 7.63037,
    "GYD": 209.215,
    "HKD": 7.8328,
    "HNL": 26.6295,
    "HRK": 6.40115,
    "HTG": 130.812,
    "HUF": 303.339,
    "IDR": 17331.3,
    "ILS": 2.90225,
    "IMP": 0.734187,
    "INR": 94.1662,
    "IQD": 1310,
    "IRR": 42000,
    "ISK": 122.17,
    "JEP": 0.734187,
    "JMD": 157.048,
    "JOD": 0.709,
    "JPY": 156.285,
    "KES": 129.15,
    "KGS": 87.5468,
    "KHR": 4009.5,
    "KMF": 417.963,
    "KPW": 899.998,
    "KRW": 1449.75,
    "KWD": 0.3062,
    "KYD": 0.82,
    "KZT": 463.445,
    "LAK": 21938.5,
    "LBP": 89550,
    "LKR": 321.1,
    "LRD": 183.174,
    "LSL": 16.2849,
    "LTL": -1,
    "LVL": -1,
    "LYD": 6.33375,
    "MAD": 9.1899,
    "MDL": 17.1925,
    "MGA": 4158.69,
    "MKD": 52.38,
    "MMK": 2100,
    "MNT": 3573,
    "MOP": 8.0679,
    "MRU": 39.9305,
    "MUR": 46.7175,
    "MVR": 15.3338,
    "MWK": 1734.01,
    "MXN": 17.2079,
    "MYR": 3.907,
    "MZN": 63.5627,
    "NAD": 16.2849,
    "NGN": 1358.18,
    "NIO": 36.8361,
    "NOK": 9.22833,
    "NPR": 150.67,
    "NZD": 1.67322,
    "OMR": 0.38502,
    "PAB": 1,
    "PEN": 3.4625,
    "PGK": 4.34783,
    "PHP": 60.4005,
    "PKR": 278.763,
    "PLN": 3.5938,
    "PYG": 6215,
    "QAR": 3.6409,
    "RON": 4.47347,
    "RSD": 99.72,
    "RUB": 74.7,
    "RWF": 1461,
    "SAR": 3.7507,
    "SBD": 8.02568,
    "SCR": 14.6744,
    "SDG": 600.171,
    "SEK": 9.21261,
    "SGD": 1.2656,
    "SHP": 0.735862,
    "SLL": 24131.6,
    "SOS": 571.5,
    "SRD": 37.3074,
    "STD": -1,
    "SVC": 8.75,
    "SYP": 11059.6,
    "SZL": 16.2838,
    "THB": 32.115,
    "TJS": 9.38035,
    "TMT": 3.5,
    "TND": 2.8754,
    "TOP": 2.34219,
    "TRY": 45.23,
    "TTD": 6.7097,
    "TWD": 31.386,
    "TZS": 2618.2,
    "UAH": 43.6,
    "UGX": 3735.92,
    "USD": 1,
    "UYU": 39.985,
    "UZS": 12107.5,
    "VES": 496.209,
    "VND": 26310.1,
    "VUV": 117.655,
    "WST": 2.69251,
    "XAF": 557.284,
    "XAG": -1,
    "XAU": -1,
    "XCD": 2.7,
    "XOF": 557.284,
    "XPF": 101.52,
    "YER": 238.54,
    "ZAR": 16.2836,
    "ZMW": 19.0072,
    "ZWL": 64009.4
  }
}